{
  "battery-empty": 97,
  "battery-full": 98,
  "ic-add": 99,
  "ic-alltype": 100,
  "ic-arrow-circle-left": 101,
  "ic-arrow-circle-right": 102,
  "ic-arrow-down": 103,
  "ic-arrow-down-1": 104,
  "ic-arrow-left": 105,
  "ic-arrow-right": 106,
  "ic-arrow-right-1": 107,
  "ic-arrow-up-1": 108,
  "ic-attach-no-border": 109,
  "ic-attach-square": 110,
  "ic-avt": 111,
  "ic-badminton": 112,
  "ic-bathroom": 113,
  "ic-big-close": 114,
  "ic-bold-add-square": 115,
  "ic-bold-calender-tick": 116,
  "ic-bold-call": 117,
  "ic-bold-check-square": 118,
  "ic-bold-close-square": 119,
  "ic-bold-coin": 120,
  "ic-bold-community": 121,
  "ic-bold-danger": 122,
  "ic-bold-document-download": 65,
  "ic-bold-export": 66,
  "ic-bold-flag": 67,
  "ic-bold-flash": 68,
  "ic-bold-flash-slash": 69,
  "ic-bold-gallery-add": 70,
  "ic-bold-gas": 71,
  "ic-bold-heart": 72,
  "ic-bold-history": 73,
  "ic-bold-home-3": 74,
  "ic-bold-home-hashtag": 75,
  "ic-bold-horizontal-more": 76,
  "ic-bold-info-square": 77,
  "ic-bold-location": 78,
  "ic-bold-mailbox": 79,
  "ic-bold-money-recive": 80,
  "ic-bold-more-circle": 81,
  "ic-bold-mybooking": 82,
  "ic-bold-pin": 83,
  "ic-bold-profile-circle": 84,
  "ic-bold-rate-star": 85,
  "ic-bold-receipt": 86,
  "ic-bold-receipt-item": 87,
  "ic-bold-refresh-circle": 88,
  "ic-bold-scan": 89,
  "ic-bold-send": 90,
  "ic-bold-setting-2": 48,
  "ic-bold-share": 49,
  "ic-bold-sorter": 50,
  "ic-bold-star": 51,
  "ic-bold-tick-circle": 52,
  "ic-bold-tick-piggy": 53,
  "ic-bold-trash-square": 54,
  "ic-bold-triangle-down": 55,
  "ic-bold-user-octagon": 56,
  "ic-bold-user-square": 57,
  "ic-bold-wallet": 33,
  "ic-bold-wallet-money": 34,
  "ic-bold-water": 35,
  "ic-box": 36,
  "ic-box-add": 37,
  "ic-briefcase": 38,
  "ic-brifecase-tick": 39,
  "ic-building-4": 40,
  "ic-calendar": 41,
  "ic-calendar-remove": 42,
  "ic-calendar-tick": 43,
  "ic-camera": 44,
  "ic-cart-2": 45,
  "ic-chart": 46,
  "ic-cleaning": 47,
  "ic-clipboard-close": 58,
  "ic-clipboard-text": 59,
  "ic-clipboard-tick": 60,
  "ic-clock": 61,
  "ic-colive": 62,
  "ic-collapse": 63,
  "ic-completed": 64,
  "ic-contract": 91,
  "ic-copy": 93,
  "ic-customer-service": 94,
  "ic-danger": 95,
  "ic-devices-electronic": 96,
  "ic-discount": 123,
  "ic-discount-circle": 124,
  "ic-document-copy": 125,
  "ic-document-text": 126,
  "ic-drink": 92,
  "ic-edit-2": 57344,
  "ic-element-3": 57345,
  "ic-emoji-happy": 57346,
  "ic-emoji-normal-relax": 57347,
  "ic-empty-wallet-time": 57348,
  "ic-emptybox": 57349,
  "ic-event": 57350,
  "ic-eye": 57351,
  "ic-eye-slash": 57352,
  "ic-filter": 57353,
  "ic-fixdesk": 57354,
  "ic-food": 57355,
  "ic-gallery": 57356,
  "ic-getdirection": 57357,
  "ic-global": 57358,
  "ic-global-search": 57359,
  "ic-gps": 57360,
  "ic-greaterandequal": 57361,
  "ic-heart": 57362,
  "ic-home-3": 57363,
  "ic-home-hashtag": 57364,
  "ic-hostel": 57365,
  "ic-hotdesk": 57366,
  "ic-hotel": 57367,
  "ic-info": 57368,
  "ic-kitchen": 57369,
  "ic-link-2": 57370,
  "ic-list": 57371,
  "ic-location": 57372,
  "ic-login": 57373,
  "ic-logout": 57374,
  "ic-mailbox": 57375,
  "ic-man": 57376,
  "ic-map": 57377,
  "ic-meetingroom": 57378,
  "ic-message": 57379,
  "ic-message-2": 57380,
  "ic-message-notif": 57381,
  "ic-message-text": 57382,
  "ic-message-time": 57383,
  "ic-messages": 57384,
  "ic-minus-square": 57385,
  "ic-mobile": 57386,
  "ic-more-circle": 57387,
  "ic-motel": 57388,
  "ic-music-play": 57389,
  "ic-mybooking": 57390,
  "ic-note": 57391,
  "ic-notification-bing": 57392,
  "ic-notification-status": 57393,
  "ic-outline-arrow-left": 57394,
  "ic-outline-arrow-up": 57395,
  "ic-outline-check-square": 57396,
  "ic-outline-close-circle": 57397,
  "ic-outline-community": 57398,
  "ic-outline-history": 57399,
  "ic-outline-info-square": 57400,
  "ic-outline-plus-circle": 57401,
  "ic-paymentmethod": 57402,
  "ic-people-community": 57403,
  "ic-personalcard": 57404,
  "ic-pin": 57405,
  "ic-printer": 57406,
  "ic-private-office": 57407,
  "ic-profile-circle": 57408,
  "ic-question": 57409,
  "ic-read": 57410,
  "ic-receipt-2": 57411,
  "ic-receipt-text": 57412,
  "ic-save": 57413,
  "ic-scan": 57414,
  "ic-search-normal": 57415,
  "ic-seating": 57416,
  "ic-setting-2": 57417,
  "ic-share": 57418,
  "ic-shield-tick": 57419,
  "ic-sidebar-right": 57420,
  "ic-smart-car-transportation": 57421,
  "ic-smart-lock": 57422,
  "ic-sms-openmail": 57423,
  "ic-sms-star": 57424,
  "ic-soccerfield": 57425,
  "ic-sort": 57426,
  "ic-sorter": 57427,
  "ic-sun-other": 57428,
  "ic-tabletennis": 57429,
  "ic-tag-2": 57430,
  "ic-tennis": 57431,
  "ic-tick-2": 57432,
  "ic-timer": 57433,
  "ic-timer-1": 57434,
  "ic-trash": 57435,
  "ic-unconfirmed": 57436,
  "ic-unpin": 57437,
  "ic-user-square": 57438,
  "ic-user-tick": 57439,
  "ic-virtual-office": 57440,
  "ic-wallet-minus": 57441,
  "ic-wallet-money": 57442,
  "ic-warning-2": 57443,
  "ic-washing": 57444,
  "ic-wifi": 57445,
  "ic-woman": 57446,
  "language-square": 57447,
  "password-check": 57448,
  "share-2": 57449,
  "shield": 57450,
  "user-remove": 57451
}